pwndoc_mcp_server/__init__.py
pwndoc_mcp_server/cli.py
pwndoc_mcp_server/client.py
pwndoc_mcp_server/config.py
pwndoc_mcp_server/logging_config.py
pwndoc_mcp_server/mcp_installer.py
pwndoc_mcp_server/server.py
pwndoc_mcp_server/version.py
pwndoc_mcp_server-1.0.9.dist-info/METADATA
pwndoc_mcp_server-1.0.9.dist-info/WHEEL
pwndoc_mcp_server-1.0.9.dist-info/entry_points.txt
pwndoc_mcp_server-1.0.9.dist-info/RECORD
